Systolic Arrays/Systolic Array Design for Matrix Multiplication/src/pe_block.sv
module pe_block #(
    parameter ARRAY_SIZE = 4,
    parameter DW_IN = 8,
    parameter DW_OUT = 2*DW_IN + $clog2(ARRAY_SIZE)
)(
    input logic clk,
    input logic rst_n,

    input logic [DW_IN-1:0] a_in,
    input logic [DW_IN-1:0] b_in,

    output logic [DW_IN-1:0] a_out,
    output logic [DW_IN-1:0] b_out,

    output logic [DW_OUT-1:0] p_out
);

    logic signed [2*DW_IN-1:0] mult;
    logic signed [DW_OUT-1:0] p_acc;

    always_ff @(posedge clk) begin
        if(~rst_n) begin
            a_out <= 'd0;
            b_out <= 'd0;

            p_acc <= 'd0;
        end
        else begin
            a_out <= a_in;
            b_out <= b_in;

            p_acc <= $signed(p_acc) + $signed(mult);
        end
    end

    assign mult = $signed(a_in) * $signed(b_in);
    assign p_out = p_acc;

endmodule

Systolic Arrays/Systolic Array Design for Matrix Multiplication/src/Systolic_Array_4x4_Matrix_Multiplication.sv
// `include "pe_block.sv"

module Systolic_Array_4x4_Matrix_Multiplication #(
  parameter ARRAY_SIZE = 4,
  parameter DW_IN = 8,
  parameter DW_OUT = 2*DW_IN + $clog2(ARRAY_SIZE)
)(
  input logic clk,
  input logic rst_n,
  //
  input logic [DW_IN-1:0] A00, A10, A20, A30,
  input logic [DW_IN-1:0] B00, B01, B02, B03,
  //
  output logic [DW_OUT-1:0] C00, C01, C02, C03, 
  output logic [DW_OUT-1:0] C10, C11, C12, C13,   
  output logic [DW_OUT-1:0] C20, C21, C22, C23,
  output logic [DW_OUT-1:0] C30, C31, C32, C33,

  output logic done
);

logic signed [DW_IN-1:0] A00_d, A10_d, A20_d, A30_d;
logic signed [DW_IN-1:0] B00_d, B01_d, B02_d, B03_d;

logic signed [DW_IN-1:0] A00_2d, A10_2d, A20_2d, A30_2d;
logic signed [DW_IN-1:0] B00_2d, B01_2d, B02_2d, B03_2d;

logic signed [DW_IN-1:0] A00_3d, A10_3d, A20_3d, A30_3d;
logic signed [DW_IN-1:0] B00_3d, B01_3d, B02_3d, B03_3d;
  
logic [3:0] count;

pe_block inst_pe_00 (.clk(clk), .rst_n(rst_n), .a_in(A00), .b_in(B00), .a_out(A00_d), .b_out(B00_d), .p_out(C00));

pe_block inst_pe_01 (.clk(clk), .rst_n(rst_n), .a_in(A00_d),  .b_in(B01), .a_out(A00_2d), .b_out(B01_d), .p_out(C01));
pe_block inst_pe_02 (.clk(clk), .rst_n(rst_n), .a_in(A00_2d), .b_in(B02), .a_out(A00_3d), .b_out(B02_d), .p_out(C02));
pe_block inst_pe_03 (.clk(clk), .rst_n(rst_n), .a_in(A00_3d), .b_in(B03), .a_out(),       .b_out(B03_d), .p_out(C03));

pe_block inst_pe_10 (.clk(clk), .rst_n(rst_n), .a_in(A10), .b_in(B00_d),  .a_out(A10_d), .b_out(B00_2d), .p_out(C10));
pe_block inst_pe_20 (.clk(clk), .rst_n(rst_n), .a_in(A20), .b_in(B00_2d), .a_out(A20_d), .b_out(B00_3d), .p_out(C20));
pe_block inst_pe_30 (.clk(clk), .rst_n(rst_n), .a_in(A30), .b_in(B00_3d), .a_out(A30_d), .b_out(),       .p_out(C30));

pe_block inst_pe_11 (.clk(clk), .rst_n(rst_n), .a_in(A10_d),  .b_in(B01_d), .a_out(A10_2d), .b_out(B01_2d), .p_out(C11));
pe_block inst_pe_12 (.clk(clk), .rst_n(rst_n), .a_in(A10_2d), .b_in(B02_d), .a_out(A10_3d), .b_out(B02_2d), .p_out(C12));
pe_block inst_pe_13 (.clk(clk), .rst_n(rst_n), .a_in(A10_3d), .b_in(B03_d), .a_out(),       .b_out(B03_2d), .p_out(C13));

pe_block inst_pe_21 (.clk(clk), .rst_n(rst_n), .a_in(A20_d),  .b_in(B01_2d), .a_out(A20_2d), .b_out(B01_3d), .p_out(C21));
pe_block inst_pe_22 (.clk(clk), .rst_n(rst_n), .a_in(A20_2d), .b_in(B02_2d), .a_out(A20_3d), .b_out(B02_3d), .p_out(C22));
pe_block inst_pe_23 (.clk(clk), .rst_n(rst_n), .a_in(A20_3d), .b_in(B03_2d), .a_out(),       .b_out(B03_3d), .p_out(C23));

pe_block inst_pe_31 (.clk(clk), .rst_n(rst_n), .a_in(A30_d),  .b_in(B01_3d), .a_out(A30_2d), .b_out(),  .p_out(C31));
pe_block inst_pe_32 (.clk(clk), .rst_n(rst_n), .a_in(A30_2d), .b_in(B02_3d), .a_out(A30_3d), .b_out(),  .p_out(C32));
pe_block inst_pe_33 (.clk(clk), .rst_n(rst_n), .a_in(A30_3d), .b_in(B03_3d), .a_out(),       .b_out(),  .p_out(C33));

	always @(posedge clk) begin
		if(~rst_n) begin
			count <= 'd0;
      done <= 'd0;
		end
		else begin
			if(count == 'd9) begin
				count <= 'd0;
        done <= 'd1;
			end
			else begin
				count <= count + 1'b1;
        done <= 'd0;
			end
		end	
	end 

endmodule

Systolic Arrays/Systolic Array Design for Matrix Multiplication/test/Systolic_Array_4x4_Matrix_Multiplication_tb.sv
// `include "../src/Systolic_Array_4x4_Matrix_Multiplication.sv"

module Systolic_Array_4x4_Matrix_Multiplication_tb ();

 parameter ARRAY_SIZE = 4;
 parameter DW_IN = 8;
 parameter DW_OUT = 2 * DW_IN + $clog2(ARRAY_SIZE);

 logic clk;
 logic rst_n;
  //
 logic signed [DW_IN-1:0] A00, A10, A20, A30;
 logic signed [DW_IN-1:0] B00, B01, B02, B03;

 logic signed [DW_OUT-1:0] C00, C01, C02, C03;
 logic signed [DW_OUT-1:0] C10, C11, C12, C13;
 logic signed [DW_OUT-1:0] C20, C21, C22, C23;
 logic signed [DW_OUT-1:0] C30, C31, C32, C33;

 logic done;

always #5 clk = ~clk; 

Systolic_Array_4x4_Matrix_Multiplication #(
    .ARRAY_SIZE(ARRAY_SIZE),
    .DW_IN(DW_IN),
    .DW_OUT(DW_OUT)
) inst_systolic_array (
    .clk(clk),
    .rst_n(rst_n),
    //
    .A00(A00), .A10(A10), .A20(A20), .A30(A30),
    .B00(B00), .B01(B01), .B02(B02), .B03(B03),
    //
    .C00(C00), .C01(C01), .C02(C02), .C03(C03), 
    .C10(C10), .C11(C11), .C12(C12), .C13(C13),   
    .C20(C20), .C21(C21), .C22(C22), .C23(C23),
    .C30(C30), .C31(C31), .C32(C32), .C33(C33),

    .done(done)
);

initial begin
    clk = 0;
    rst_n = 0;
    A00 = 8'd0; A10 = 8'd0; A20 = 8'd0; A30 = 8'd0;
    B00 = 8'd0; B01 = 8'd0; B02 = 8'd0; B03 = 8'd0;
    #10;
    rst_n = 1;
    # 150 $finish;
end

/*
// Test Vector 1
initial begin
	#13 A00 = 8'hAF;
	    B00 = 8'h63;
	#10 A00 = 8'h9E;
	    B00 = 8'hA3;
	#10 A00 = 8'h6E;
	    B00 = 8'h75;
	#10 A00 = 8'h9F;
	    B00 = 8'h08;
	#10 A00 = 8'h0;
	    B00 = 8'h0;
	#10 A00 = 8'h0;
	    B00 = 8'h0;
	#10 A00 = 8'h0;	
	    B00 = 8'h0;
end

initial begin
	#13 A10 = 8'h0;
	    B01 = 8'h0;
	#10 A10 = 8'hFF;
	    B01 = 8'hD0;
	#10 A10 = 8'h51;
	    B01 = 8'h7B;
	#10 A10 = 8'hB4;
	    B01 = 8'h21;
	#10 A10 = 8'hE0;
	    B01 = 8'h5F;
	#10 A10 = 8'h0;
	    B01 = 8'h0;
	#10 A10 = 8'h0;	
	    B01 = 8'h0;
end

initial begin
	#13 A20 = 8'h0;
	    B02 = 8'h0;
	#10 A20 = 8'h0;
	    B02 = 8'h0;
	#10 A20 = 8'hFA;
	    B02 = 8'h4D;
	#10 A20 = 8'hCB;
	    B02 = 8'hA7;
	#10 A20 = 8'h40;
	    B02 = 8'h1C;
	#10 A20 = 8'h17;
	    B02 = 8'h8F;
	#10 A20 = 8'h0;	
	    B02 = 8'h0;
end

initial begin
	#13 A30 = 8'h0;
	    B03 = 8'h0;
	#10 A30 = 8'h0;
	    B03 = 8'h0;
	#10 A30 = 8'h0;
	    B03 = 8'h0;
	#10 A30 = 8'hD2;
	    B03 = 8'hC4;
	#10 A30 = 8'hAB;
	    B03 = 8'h0F;
	#10 A30 = 8'hFD;
	    B03 = 8'h88;
	#10 A30 = 8'hFB;	
	    B03 = 8'hB1;
  #10 A30 = 8'h0;	
      B03 = 8'h0;
end
*/

// Test Vector 2
initial begin
	#13  A00 = 32'd3;
	    B00 = 32'd12;
	#10 A00 = 32'd2;
	    B00 = 32'd8;
	#10 A00 = 32'd1;
	    B00 = 32'd4;
	#10 A00 = 32'd5;
	    B00 = 32'd6;
	#10 A00 = 32'd0;
	    B00 = 32'd0;
	#10 A00 = 32'd0;
	    B00 = 32'd0;
	#10 A00 = 32'd0;	
	    B00 = 32'd0;
end

initial begin
	#13 A10 = 32'd0;
	    B01 = 32'd0;
	#10 A10 = 32'd7;
	    B01 = 32'd13;
	#10 A10 = 32'd6;
	    B01 = 32'd9;
	#10 A10 = 32'd5;
	    B01 = 32'd5;
	#10 A10 = 32'd4;
	    B01 = 32'd1;
	#10 A10 = 32'd0;
	    B01 = 32'd0;
	#10 A10 = 32'd0;	
	    B01 = 32'd0;
end

initial begin
	#13  A20 = 32'd0;
	    B02 = 32'd0;
	#10 A20 = 32'd0;
	    B02 = 32'd0;
	#10 A20 = 32'd11;
	    B02 = 32'd14;
	#10 A20 = 32'd10;
	    B02 = 32'd10;
	#10 A20 = 32'd9;
	    B02 = 32'd6;
	#10 A20 = 32'd8;
	    B02 = 32'd2;
	#10 A20 = 32'd0;	
	    B02 = 32'd0;
end

initial begin
	#13  A30 = 32'd0;
	    B03 = 32'd0;
	#10 A30 = 32'd0;
	    B03 = 32'd0;
	#10 A30 = 32'd0;
	    B03 = 32'd0;
	#10 A30 = 32'd15;
	    B03 = 32'd15;
	#10 A30 = 32'd14;
	    B03 = 32'd11;
	#10 A30 = 32'd13;
	    B03 = 32'd7;
	#10 A30 = 32'd12;	
	    B03 = 32'd3;
  #10 A30 = 32'd0;	
      B03 = 32'd0;    
end

initial begin
	$dumpfile("wave_mul.vcd");
	$dumpvars(0, Systolic_Array_4x4_Matrix_Multiplication_tb);
end

endmodule

Systolic Arrays/Systolic Array Design for Matrix Multiplication/wave_mul.vcd
$date
	Mon Jan 26 16:57:57 2026
$end
$version
	Icarus Verilog
$end
$timescale
	1s
$end
$scope module Systolic_Array_4x4_Matrix_Multiplication_tb $end
$var wire 1 ! done $end
$var wire 18 " C33 [17:0] $end
$var wire 18 # C32 [17:0] $end
$var wire 18 $ C31 [17:0] $end
$var wire 18 % C30 [17:0] $end
$var wire 18 & C23 [17:0] $end
$var wire 18 ' C22 [17:0] $end
$var wire 18 ( C21 [17:0] $end
$var wire 18 ) C20 [17:0] $end
$var wire 18 * C13 [17:0] $end
$var wire 18 + C12 [17:0] $end
$var wire 18 , C11 [17:0] $end
$var wire 18 - C10 [17:0] $end
$var wire 18 . C03 [17:0] $end
$var wire 18 / C02 [17:0] $end
$var wire 18 0 C01 [17:0] $end
$var wire 18 1 C00 [17:0] $end
$var parameter 32 2 ARRAY_SIZE $end
$var parameter 32 3 DW_IN $end
$var parameter 65 4 DW_OUT $end
$var reg 8 5 A00 [7:0] $end
$var reg 8 6 A10 [7:0] $end
$var reg 8 7 A20 [7:0] $end
$var reg 8 8 A30 [7:0] $end
$var reg 8 9 B00 [7:0] $end
$var reg 8 : B01 [7:0] $end
$var reg 8 ; B02 [7:0] $end
$var reg 8 < B03 [7:0] $end
$var reg 1 = clk $end
$var reg 1 > rst_n $end
$scope module inst_systolic_array $end
$var wire 8 ? A00 [7:0] $end
$var wire 8 @ A10 [7:0] $end
$var wire 8 A A20 [7:0] $end
$var wire 8 B A30 [7:0] $end
$var wire 8 C B00 [7:0] $end
$var wire 8 D B01 [7:0] $end
$var wire 8 E B02 [7:0] $end
$var wire 8 F B03 [7:0] $end
$var wire 1 = clk $end
$var wire 1 > rst_n $end
$var wire 18 G C33 [17:0] $end
$var wire 18 H C32 [17:0] $end
$var wire 18 I C31 [17:0] $end
$var wire 18 J C30 [17:0] $end
$var wire 18 K C23 [17:0] $end
$var wire 18 L C22 [17:0] $end
$var wire 18 M C21 [17:0] $end
$var wire 18 N C20 [17:0] $end
$var wire 18 O C13 [17:0] $end
$var wire 18 P C12 [17:0] $end
$var wire 18 Q C11 [17:0] $end
$var wire 18 R C10 [17:0] $end
$var wire 18 S C03 [17:0] $end
$var wire 18 T C02 [17:0] $end
$var wire 18 U C01 [17:0] $end
$var wire 18 V C00 [17:0] $end
$var wire 8 W B03_d [7:0] $end
$var wire 8 X B03_3d [7:0] $end
$var wire 8 Y B03_2d [7:0] $end
$var wire 8 Z B02_d [7:0] $end
$var wire 8 [ B02_3d [7:0] $end
$var wire 8 \ B02_2d [7:0] $end
$var wire 8 ] B01_d [7:0] $end
$var wire 8 ^ B01_3d [7:0] $end
$var wire 8 _ B01_2d [7:0] $end
$var wire 8 ` B00_d [7:0] $end
$var wire 8 a B00_3d [7:0] $end
$var wire 8 b B00_2d [7:0] $end
$var wire 8 c A30_d [7:0] $end
$var wire 8 d A30_3d [7:0] $end
$var wire 8 e A30_2d [7:0] $end
$var wire 8 f A20_d [7:0] $end
$var wire 8 g A20_3d [7:0] $end
$var wire 8 h A20_2d [7:0] $end
$var wire 8 i A10_d [7:0] $end
$var wire 8 j A10_3d [7:0] $end
$var wire 8 k A10_2d [7:0] $end
$var wire 8 l A00_d [7:0] $end
$var wire 8 m A00_3d [7:0] $end
$var wire 8 n A00_2d [7:0] $end
$var parameter 32 o ARRAY_SIZE $end
$var parameter 32 p DW_IN $end
$var parameter 65 q DW_OUT $end
$var reg 4 r count [3:0] $end
$var reg 1 ! done $end
$scope module inst_pe_00 $end
$var wire 8 s a_in [7:0] $end
$var wire 8 t b_in [7:0] $end
$var wire 1 = clk $end
$var wire 18 u p_out [17:0] $end
$var wire 1 > rst_n $end
$var wire 16 v mult [15:0] $end
$var parameter 32 w ARRAY_SIZE $end
$var parameter 32 x DW_IN $end
$var parameter 65 y DW_OUT $end
$var reg 8 z a_out [7:0] $end
$var reg 8 { b_out [7:0] $end
$var reg 18 | p_acc [17:0] $end
$upscope $end
$scope module inst_pe_01 $end
$var wire 8 } a_in [7:0] $end
$var wire 8 ~ b_in [7:0] $end
$var wire 1 = clk $end
$var wire 18 !" p_out [17:0] $end
$var wire 1 > rst_n $end
$var wire 16 "" mult [15:0] $end
$var parameter 32 #" ARRAY_SIZE $end
$var parameter 32 $" DW_IN $end
$var parameter 65 %" DW_OUT $end
$var reg 8 &" a_out [7:0] $end
$var reg 8 '" b_out [7:0] $end
$var reg 18 (" p_acc [17:0] $end
$upscope $end
$scope module inst_pe_02 $end
$var wire 8 )" a_in [7:0] $end
$var wire 8 *" b_in [7:0] $end
$var wire 1 = clk $end
$var wire 18 +" p_out [17:0] $end
$var wire 1 > rst_n $end
$var wire 16 ," mult [15:0] $end
$var parameter 32 -" ARRAY_SIZE $end
$var parameter 32 ." DW_IN $end
$var parameter 65 /" DW_OUT $end
$var reg 8 0" a_out [7:0] $end
$var reg 8 1" b_out [7:0] $end
$var reg 18 2" p_acc [17:0] $end
$upscope $end
$scope module inst_pe_03 $end
$var wire 8 3" a_in [7:0] $end
$var wire 8 4" b_in [7:0] $end
$var wire 1 = clk $end
$var wire 18 5" p_out [17:0] $end
$var wire 1 > rst_n $end
$var wire 16 6" mult [15:0] $end
$var parameter 32 7" ARRAY_SIZE $end
$var parameter 32 8" DW_IN $end
$var parameter 65 9" DW_OUT $end
$var reg 8 :" a_out [7:0] $end
$var reg 8 ;" b_out [7:0] $end
$var reg 18 <" p_acc [17:0] $end
$upscope $end
$scope module inst_pe_10 $end
$var wire 8 =" a_in [7:0] $end
$var wire 8 >" b_in [7:0] $end
$var wire 1 = clk $end
$var wire 18 ?" p_out [17:0] $end
$var wire 1 > rst_n $end
$var wire 16 @" mult [15:0] $end
$var parameter 32 A" ARRAY_SIZE $end
$var parameter 32 B" DW_IN $end
$var parameter 65 C" DW_OUT $end
$var reg 8 D" a_out [7:0] $end
$var reg 8 E" b_out [7:0] $end
$var reg 18 F" p_acc [17:0] $end
$upscope $end
$scope module inst_pe_11 $end
$var wire 8 G" a_in [7:0] $end
$var wire 8 H" b_in [7:0] $end
$var wire 1 = clk $end
$var wire 18 I" p_out [17:0] $end
$var wire 1 > rst_n $end
$var wire 16 J" mult [15:0] $end
$var parameter 32 K" ARRAY_SIZE $end
$var parameter 32 L" DW_IN $end
$var parameter 65 M" DW_OUT $end
$var reg 8 N" a_out [7:0] $end
$var reg 8 O" b_out [7:0] $end
$var reg 18 P" p_acc [17:0] $end
$upscope $end
$scope module inst_pe_12 $end
$var wire 8 Q" a_in [7:0] $end
$var wire 8 R" b_in [7:0] $end
$var wire 1 = clk $end
$var wire 18 S" p_out [17:0] $end
$var wire 1 > rst_n $end
$var wire 16 T" mult [15:0] $end
$var parameter 32 U" ARRAY_SIZE $end
$var parameter 32 V" DW_IN $end
$var parameter 65 W" DW_OUT $end
$var reg 8 X" a_out [7:0] $end
$var reg 8 Y" b_out [7:0] $end
$var reg 18 Z" p_acc [17:0] $end
$upscope $end
$scope module inst_pe_13 $end
$var wire 8 [" a_in [7:0] $end
$var wire 8 \" b_in [7:0] $end
$var wire 1 = clk $end
$var wire 18 ]" p_out [17:0] $end
$var wire 1 > rst_n $end
$var wire 16 ^" mult [15:0] $end
$var parameter 32 _" ARRAY_SIZE $end
$var parameter 32 `" DW_IN $end
$var parameter 65 a" DW_OUT $end
$var reg 8 b" a_out [7:0] $end
$var reg 8 c" b_out [7:0] $end
$var reg 18 d" p_acc [17:0] $end
$upscope $end
$scope module inst_pe_20 $end
$var wire 8 e" a_in [7:0] $end
$var wire 8 f" b_in [7:0] $end
$var wire 1 = clk $end
$var wire 18 g" p_out [17:0] $end
$var wire 1 > rst_n $end
$var wire 16 h" mult [15:0] $end
$var parameter 32 i" ARRAY_SIZE $end
$var parameter 32 j" DW_IN $end
$var parameter 65 k" DW_OUT $end
$var reg 8 l" a_out [7:0] $end
$var reg 8 m" b_out [7:0] $end
$var reg 18 n" p_acc [17:0] $end
$upscope $end
$scope module inst_pe_21 $end
$var wire 8 o" a_in [7:0] $end
$var wire 8 p" b_in [7:0] $end
$var wire 1 = clk $end
$var wire 18 q" p_out [17:0] $end
$var wire 1 > rst_n $end
$var wire 16 r" mult [15:0] $end
$var parameter 32 s" ARRAY_SIZE $end
$var parameter 32 t" DW_IN $end
$var parameter 65 u" DW_OUT $end
$var reg 8 v" a_out [7:0] $end
$var reg 8 w" b_out [7:0] $end
$var reg 18 x" p_acc [17:0] $end
$upscope $end
$scope module inst_pe_22 $end
$var wire 8 y" a_in [7:0] $end
$var wire 8 z" b_in [7:0] $end
$var wire 1 = clk $end
$var wire 18 {" p_out [17:0] $end
$var wire 1 > rst_n $end
$var wire 16 |" mult [15:0] $end
$var parameter 32 }" ARRAY_SIZE $end
$var parameter 32 ~" DW_IN $end
$var parameter 65 !# DW_OUT $end
$var reg 8 "# a_out [7:0] $end
$var reg 8 ## b_out [7:0] $end
$var reg 18 $# p_acc [17:0] $end
$upscope $end
$scope module inst_pe_23 $end
$var wire 8 %# a_in [7:0] $end
$var wire 8 &# b_in [7:0] $end
$var wire 1 = clk $end
$var wire 18 '# p_out [17:0] $end
$var wire 1 > rst_n $end
$var wire 16 (# mult [15:0] $end
$var parameter 32 )# ARRAY_SIZE $end
$var parameter 32 *# DW_IN $end
$var parameter 65 +# DW_OUT $end
$var reg 8 ,# a_out [7:0] $end
$var reg 8 -# b_out [7:0] $end
$var reg 18 .# p_acc [17:0] $end
$upscope $end
$scope module inst_pe_30 $end
$var wire 8 /# a_in [7:0] $end
$var wire 8 0# b_in [7:0] $end
$var wire 1 = clk $end
$var wire 18 1# p_out [17:0] $end
$var wire 1 > rst_n $end
$var wire 16 2# mult [15:0] $end
$var parameter 32 3# ARRAY_SIZE $end
$var parameter 32 4# DW_IN $end
$var parameter 65 5# DW_OUT $end
$var reg 8 6# a_out [7:0] $end
$var reg 8 7# b_out [7:0] $end
$var reg 18 8# p_acc [17:0] $end
$upscope $end
$scope module inst_pe_31 $end
$var wire 8 9# a_in [7:0] $end
$var wire 8 :# b_in [7:0] $end
$var wire 1 = clk $end
$var wire 18 ;# p_out [17:0] $end
$var wire 1 > rst_n $end
$var wire 16 <# mult [15:0] $end
$var parameter 32 =# ARRAY_SIZE $end
$var parameter 32 ># DW_IN $end
$var parameter 65 ?# DW_OUT $end
$var reg 8 @# a_out [7:0] $end
$var reg 8 A# b_out [7:0] $end
$var reg 18 B# p_acc [17:0] $end
$upscope $end
$scope module inst_pe_32 $end
$var wire 8 C# a_in [7:0] $end
$var wire 8 D# b_in [7:0] $end
$var wire 1 = clk $end
$var wire 18 E# p_out [17:0] $end
$var wire 1 > rst_n $end
$var wire 16 F# mult [15:0] $end
$var parameter 32 G# ARRAY_SIZE $end
$var parameter 32 H# DW_IN $end
$var parameter 65 I# DW_OUT $end
$var reg 8 J# a_out [7:0] $end
$var reg 8 K# b_out [7:0] $end
$var reg 18 L# p_acc [17:0] $end
$upscope $end
$scope module inst_pe_33 $end
$var wire 8 M# a_in [7:0] $end
$var wire 8 N# b_in [7:0] $end
$var wire 1 = clk $end
$var wire 18 O# p_out [17:0] $end
$var wire 1 > rst_n $end
$var wire 16 P# mult [15:0] $end
$var parameter 32 Q# ARRAY_SIZE $end
$var parameter 32 R# DW_IN $end
$var parameter 65 S# DW_OUT $end
$var reg 8 T# a_out [7:0] $end
$var reg 8 U# b_out [7:0] $end
$var reg 18 V# p_acc [17:0] $end
$upscope $end
$upscope $end
$upscope $end
$enddefinitions $end
$comment Show the parameter values. $end
$dumpall
b10010 S#
b1000 R#
b100 Q#
b10010 I#
b1000 H#
b100 G#
b10010 ?#
b1000 >#
b100 =#
b10010 5#
b1000 4#
b100 3#
b10010 +#
b1000 *#
b100 )#
b10010 !#
b1000 ~"
b100 }"
b10010 u"
b1000 t"
b100 s"
b10010 k"
b1000 j"
b100 i"
b10010 a"
b1000 `"
b100 _"
b10010 W"
b1000 V"
b100 U"
b10010 M"
b1000 L"
b100 K"
b10010 C"
b1000 B"
b100 A"
b10010 9"
b1000 8"
b100 7"
b10010 /"
b1000 ."
b100 -"
b10010 %"
b1000 $"
b100 #"
b10010 y
b1000 x
b100 w
b10010 q
b1000 p
b100 o
b10010 4
b1000 3
b100 2
$end
#0
$dumpvars
bx V#
bx U#
bx T#
bx P#
bx O#
bx N#
bx M#
bx L#
bx K#
bx J#
bx F#
bx E#
bx D#
bx C#
bx B#
bx A#
bx @#
bx <#
bx ;#
bx :#
bx 9#
bx 8#
bx 7#
bx 6#
bx 2#
bx 1#
bx 0#
b0 /#
bx .#
bx -#
bx ,#
bx (#
bx '#
bx &#
bx %#
bx $#
bx ##
bx "#
bx |"
bx {"
bx z"
bx y"
bx x"
bx w"
bx v"
bx r"
bx q"
bx p"
bx o"
bx n"
bx m"
bx l"
bx h"
bx g"
bx f"
b0 e"
bx d"
bx c"
bx b"
bx ^"
bx ]"
bx \"
bx ["
bx Z"
bx Y"
bx X"
bx T"
bx S"
bx R"
bx Q"
bx P"
bx O"
bx N"
bx J"
bx I"
bx H"
bx G"
bx F"
bx E"
bx D"
bx @"
bx ?"
bx >"
b0 ="
bx <"
bx ;"
bx :"
bx 6"
bx 5"
b0 4"
bx 3"
bx 2"
bx 1"
bx 0"
bx ,"
bx +"
b0 *"
bx )"
bx ("
bx '"
bx &"
bx ""
bx !"
b0 ~
bx }
bx |
bx {
bx z
b0 v
bx u
b0 t
b0 s
bx r
bx n
bx m
bx l
bx k
bx j
bx i
bx h
bx g
bx f
bx e
bx d
bx c
bx b
bx a
bx `
bx _
bx ^
bx ]
bx \
bx [
bx Z
bx Y
bx X
bx W
bx V
bx U
bx T
bx S
bx R
bx Q
bx P
bx O
bx N
bx M
bx L
bx K
bx J
bx I
bx H
bx G
b0 F
b0 E
b0 D
b0 C
b0 B
b0 A
b0 @
b0 ?
0>
0=
b0 <
b0 ;
b0 :
b0 9
b0 8
b0 7
b0 6
b0 5
bx 1
bx 0
bx /
bx .
bx -
bx ,
bx +
bx *
bx )
bx (
bx '
bx &
bx %
bx $
bx #
bx "
x!
$end
#5
b0 1
b0 V
b0 u
b0 |
b0 @"
b0 `
b0 {
b0 >"
b0 ""
b0 l
b0 z
b0 }
b0 0
b0 U
b0 !"
b0 ("
b0 J"
b0 ]
b0 '"
b0 H"
b0 ,"
b0 n
b0 &"
b0 )"
b0 /
b0 T
b0 +"
b0 2"
b0 T"
b0 Z
b0 1"
b0 R"
b0 6"
b0 m
b0 0"
b0 3"
b0 .
b0 S
b0 5"
b0 <"
b0 ^"
b0 W
b0 ;"
b0 \"
b0 :"
b0 -
b0 R
b0 ?"
b0 F"
b0 h"
b0 b
b0 E"
b0 f"
b0 i
b0 D"
b0 G"
b0 )
b0 N
b0 g"
b0 n"
b0 2#
b0 a
b0 m"
b0 0#
b0 r"
b0 f
b0 l"
b0 o"
b0 %
b0 J
b0 1#
b0 8#
b0 7#
b0 <#
b0 c
b0 6#
b0 9#
b0 ,
b0 Q
b0 I"
b0 P"
b0 _
b0 O"
b0 p"
b0 k
b0 N"
b0 Q"
b0 +
b0 P
b0 S"
b0 Z"
b0 |"
b0 \
b0 Y"
b0 z"
b0 j
b0 X"
b0 ["
b0 *
b0 O
b0 ]"
b0 d"
b0 (#
b0 Y
b0 c"
b0 &#
b0 b"
b0 (
b0 M
b0 q"
b0 x"
b0 ^
b0 w"
b0 :#
b0 h
b0 v"
b0 y"
b0 '
b0 L
b0 {"
b0 $#
b0 F#
b0 [
b0 ##
b0 D#
b0 g
b0 "#
b0 %#
b0 &
b0 K
b0 '#
b0 .#
b0 P#
b0 X
b0 -#
b0 N#
b0 ,#
b0 $
b0 I
b0 ;#
b0 B#
b0 A#
b0 e
b0 @#
b0 C#
b0 #
b0 H
b0 E#
b0 L#
b0 K#
b0 d
b0 J#
b0 M#
b0 "
b0 G
b0 O#
b0 V#
b0 U#
b0 T#
0!
b0 r
1=
#10
0=
1>
#13
b100100 v
b1100 9
b1100 C
b1100 t
b11 5
b11 ?
b11 s
#15
b1 r
b100100 1
b100100 V
b100100 u
b100100 |
b1100 `
b1100 {
b1100 >"
b11 l
b11 z
b11 }
1=
#20
0=
#23
b100111 ""
b1101 :
b1101 D
b1101 ~
b1010100 @"
b111 6
b111 @
b111 ="
b1000 9
b1000 C
b1000 t
b10000 v
b10 5
b10 ?
b10 s
#25
b110100 1
b110100 V
b110100 u
b110100 |
b111000 @"
b1000 `
b1000 {
b1000 >"
b11010 ""
b10 l
b10 z
b10 }
b100111 0
b100111 U
b100111 !"
b100111 ("
b1011011 J"
b1101 ]
b1101 '"
b1101 H"
b11 n
b11 &"
b11 )"
b1010100 -
b1010100 R
b1010100 ?"
b1010100 F"
b1100 b
b1100 E"
b1100 f"
b111 i
b111 D"
b111 G"
b10 r
1=
#30
0=
#33
b101010 ,"
b1110 ;
b1110 E
b1110 *"
b10000100 h"
b1011 7
b1011 A
b1011 e"
b10010 ""
b1001 :
b1001 D
b1001 ~
b110000 @"
b110 6
b110 @
b110 ="
b100 9
b100 C
b100 t
b100 v
b1 5
b1 ?
b1 s
#35
b11 r
b1011011 ,
b1011011 Q
b1011011 I"
b1011011 P"
b10001111 r"
b1101 _
b1101 O"
b1101 p"
b1100010 T"
b111 k
b111 N"
b111 Q"
b10000100 )
b10000100 N
b10000100 g"
b10000100 n"
b1100 a
b1100 m"
b1100 0#
b1011 f
b1011 l"
b1011 o"
b10000100 -
b10000100 R
b10000100 ?"
b10000100 F"
b1011000 h"
b1000 b
b1000 E"
b1000 f"
b110 i
b110 D"
b110 G"
b101010 /
b101010 T
b101010 +"
b101010 2"
b1110 Z
b1110 1"
b1110 R"
b11 m
b11 0"
b11 3"
b111001 0
b111001 U
b111001 !"
b111001 ("
b110110 J"
b1001 ]
b1001 '"
b1001 H"
b11100 ,"
b10 n
b10 &"
b10 )"
b111000 1
b111000 V
b111000 u
b111000 |
b11000 @"
b100 `
b100 {
b100 >"
b1001 ""
b1 l
b1 z
b1 }
1=
#40
0=
#43
b101101 6"
b1111 <
b1111 F
b1111 4"
b10110100 2#
b1111 8
b1111 B
b1111 /#
b10100 ,"
b1010 ;
b1010 E
b1010 *"
b1010000 h"
b1010 7
b1010 A
b1010 e"
b101 ""
b101 :
b101 D
b101 ~
b10100 @"
b101 6
b101 @
b101 ="
b110 9
b110 C
b110 t
b11110 v
b101 5
b101 ?
b101 s
